[{"title": "\ucc29\ud55c \uc721\uac1c\uc7a5vs\uba54\ubc00\uad6d\uc218", "link": "", "category": "\uc74c\uc2dd\uc810>\ud55c\uc2dd", "description": "", "telephone": "031-431-4005", "address": "\uacbd\uae30\ub3c4 \uc2dc\ud765\uc2dc \uc815\uc655\ub3d9 2042-16", "roadAddress": "\uacbd\uae30\ub3c4 \uc2dc\ud765\uc2dc \uc624\uc774\ub3c4\ub85c 249", "mapx": "284056", "mapy": "527339"}, {"title": "\uc721\uc7a5\uc7a5\uc774", "link": "", "category": "\ud55c\uc2dd>\uc721\ub958,\uace0\uae30\uc694\ub9ac", "description": "", "telephone": "031-433-0092", "address": "\uacbd\uae30\ub3c4 \uc2dc\ud765\uc2dc \uc815\uc655\ub3d9 2513-1 \uc13c\ud130\ud504\ub77c\uc7902 2\uce35", "roadAddress": "\uacbd\uae30\ub3c4 \uc2dc\ud765\uc2dc \ubc30\uace73\ub85c 86 \uc13c\ud130\ud504\ub77c\uc7902 2\uce35", "mapx": "287697", "mapy": "530570"}, {"title": "\uc0b0\ub9c8\ub974\ucf54", "link": "http://sanmarco.modoo.at", "category": "\uc74c\uc2dd\uc810>\uc774\ud0c8\ub9ac\uc544\uc74c\uc2dd", "description": "", "telephone": "031-499-0607", "address": "\uacbd\uae30\ub3c4 \uc2dc\ud765\uc2dc \uc815\uc655\ub3d9 2537-2", "roadAddress": "\uacbd\uae30\ub3c4 \uc2dc\ud765\uc2dc \uc11c\uc6b8\ub300\ud559\ub85c278\ubc88\uae38 61 \ubc30\uace7\ubca0\ub2c8\uc2a4\uc2a4\ud018\uc5b4 1\uce35 t-5\ud638", "mapx": "287766", "mapy": "530334"}, {"title": "\uace0\uae30\ud55c\ud310", "link": "http://instagram.com/gogi9228", "category": "\ud55c\uc2dd>\uc18c\uace0\uae30\uad6c\uc774", "description": "", "telephone": "031-497-9228", "address": "\uacbd\uae30\ub3c4 \uc2dc\ud765\uc2dc \uc815\uc655\ub3d9 1881-11", "roadAddress": "\uacbd\uae30\ub3c4 \uc2dc\ud765\uc2dc \ud568\uc1a1\ub85c 15 \ud654\uc2e0\ud504\ub77c\uc790", "mapx": "287726", "mapy": "529878"}, {"title": "\ubd81\ucd0c\uc0bc\ub300\uac08\ube44 \ubc30\uace7\uc810", "link": "http://\ubd81\ucd0c\uc0bc\ub300\uac08\ube44.com", "category": "\ud55c\uc2dd>\uc721\ub958,\uace0\uae30\uc694\ub9ac", "description": "", "telephone": "031-433-1227", "address": "\uacbd\uae30\ub3c4 \uc2dc\ud765\uc2dc \uc815\uc655\ub3d9 2515", "roadAddress": "\uacbd\uae30\ub3c4 \uc2dc\ud765\uc2dc \uc11c\uc6b8\ub300\ud559\ub85c278\ubc88\uae38 19-14 2\uce35", "mapx": "287590", "mapy": "530557"}, {"title": "\ub4f1\ub300\ud69f\uc9d1", "link": "", "category": "\ud55c\uc2dd>\uc870\uac1c\uc694\ub9ac", "description": "", "telephone": "031-431-8868", "address": "\uacbd\uae30\ub3c4 \uc2dc\ud765\uc2dc \uc815\uc655\ub3d9 2003-27", "roadAddress": "\uacbd\uae30\ub3c4 \uc2dc\ud765\uc2dc \uc624\uc774\ub3c4\ub85c 161", "mapx": "283984", "mapy": "527981"}, {"title": "\uace0\uae30\uc6d0\uce59 \ubc30\uace7\uc2e0\ub3c4\uc2dc\uc810", "link": "", "category": "\ud55c\uc2dd>\uc721\ub958,\uace0\uae30\uc694\ub9ac>\uace0\uae30\uc6d0\uce59", "description": "", "telephone": "", "address": "\uacbd\uae30\ub3c4 \uc2dc\ud765\uc2dc \uc815\uc655\ub3d9 2518", "roadAddress": "\uacbd\uae30\ub3c4 \uc2dc\ud765\uc2dc \uc11c\uc6b8\ub300\ud559\ub85c278\ubc88\uae38 25-24 103\ud638", "mapx": "287673", "mapy": "530466"}, {"title": "\ud22c\ud30c\uc778\ub4dc\ud53c\ud130 \ubc30\uace7\uc810", "link": "http://instagram.com/2fp_bg", "category": "\uc74c\uc2dd\uc810>\uc774\ud0c8\ub9ac\uc544\uc74c\uc2dd", "description": "", "telephone": "", "address": "\uacbd\uae30\ub3c4 \uc2dc\ud765\uc2dc \uc815\uc655\ub3d9 2527", "roadAddress": "\uacbd\uae30\ub3c4 \uc2dc\ud765\uc2dc \uc11c\uc6b8\ub300\ud559\ub85c264\ubc88\uae38 35 \uc544\ube0c\ub274\ud504\ub791\uc13c\ud2b8\ub7f4 \uadf8\ub9b0\ub3d9 226,227\ud638", "mapx": "287570", "mapy": "530286"}, {"title": "\ucc38\ub098\ubb34\ub204\ub8fd\ub2ed", "link": "https://blog.naver.com/realchicken100", "category": "\uc74c\uc2dd\uc810>\uce58\ud0a8,\ub2ed\uac15\uc815", "description": "", "telephone": "031-319-5222", "address": "\uacbd\uae30\ub3c4 \uc2dc\ud765\uc2dc \uc815\uc655\ub3d9 1742-21", "roadAddress": "\uacbd\uae30\ub3c4 \uc2dc\ud765\uc2dc \uc911\uc2ec\uc0c1\uac003\uae38 31-1", "mapx": "288152", "mapy": "527587"}, {"title": "\uccad\ucd98\uc870\uac1c\ubcf8\uc810", "link": "", "category": "\ud55c\uc2dd>\uc870\uac1c\uc694\ub9ac", "description": "", "telephone": "031-319-5227", "address": "\uacbd\uae30\ub3c4 \uc2dc\ud765\uc2dc \uc815\uc655\ub3d9 2030-11", "roadAddress": "\uacbd\uae30\ub3c4 \uc2dc\ud765\uc2dc \uc624\uc774\ub3c4\ub85c 199-1", "mapx": "283866", "mapy": "527602"}, {"title": "\ub204\ub098\ud640\ub2ed \ubc30\uace7\ud55c\ub77c\ube44\ubc1c\ub514\uc810", "link": "http://www.noonaholdak.co.kr", "category": "\uc74c\uc2dd\uc810>\uce58\ud0a8,\ub2ed\uac15\uc815", "description": "", "telephone": "031-319-7765", "address": "\uacbd\uae30\ub3c4 \uc2dc\ud765\uc2dc \uc815\uc655\ub3d9 2566", "roadAddress": "\uacbd\uae30\ub3c4 \uc2dc\ud765\uc2dc \ubc30\uace71\ub85c 27-15", "mapx": "286311", "mapy": "529895"}, {"title": "\uc9c0\ub2c8\uce74\ub871", "link": "http://instagram.com/macarons_nuna", "category": "\uc74c\uc2dd\uc810>\uce74\ud398,\ub514\uc800\ud2b8", "description": "", "telephone": "", "address": "\uacbd\uae30\ub3c4 \uc2dc\ud765\uc2dc \uc815\uc655\ub3d9 2537-2", "roadAddress": "\uacbd\uae30\ub3c4 \uc2dc\ud765\uc2dc \uc11c\uc6b8\ub300\ud559\ub85c278\ubc88\uae38 61 \uc11c\uc601\ubca0\ub2c8\uc2a4\uc2a4\ud018\uc5b4 1\uce35 T-1", "mapx": "287775", "mapy": "530310"}, {"title": "\ud574\ube14\ub791\ub514\uc800\ud2b8", "link": "https://m.smartstore.naver.com/hbldessert?NaPm=", "category": "\uc74c\uc2dd\uc810>\uce74\ud398,\ub514\uc800\ud2b8", "description": "", "telephone": "", "address": "\uacbd\uae30\ub3c4 \uc2dc\ud765\uc2dc \uc815\uc655\ub3d9 2536-1", "roadAddress": "\uacbd\uae30\ub3c4 \uc2dc\ud765\uc2dc \uc11c\uc6b8\ub300\ud559\ub85c264\ubc88\uae38 26-32 142\ud638 \ud574\ube14\ub791\ub514\uc800\ud2b8", "mapx": "287504", "mapy": "530165"}, {"title": "\uad6c\uc2ed\ub3c4\uc528", "link": "http://www.instagram.com/ninety___degrees", "category": "\uc74c\uc2dd\uc810>\uce74\ud398,\ub514\uc800\ud2b8", "description": "", "telephone": "031-503-0799", "address": "\uacbd\uae30\ub3c4 \uc2dc\ud765\uc2dc \uc815\uc655\ub3d9 1771-31", "roadAddress": "\uacbd\uae30\ub3c4 \uc2dc\ud765\uc2dc \uc11c\uc6b8\ub300\ud559\ub85c264\ubc88\uae38 26-29 \ub2e4\uc778\ub85c\uc584\ud330\ub9ac\uc2a4 5\ucc28 109\ud638", "mapx": "287444", "mapy": "530188"}, {"title": "\uc624\uc774\ub3c4\uc804\ub9dd\ub300\uce74\ud398", "link": "https://cafe.naver.com/viewoidocafe", "category": "\uc74c\uc2dd\uc810>\uce74\ud398,\ub514\uc800\ud2b8", "description": "", "telephone": "", "address": "\uacbd\uae30\ub3c4 \uc2dc\ud765\uc2dc \uc815\uc655\ub3d9 1089-1", "roadAddress": "\uacbd\uae30\ub3c4 \uc2dc\ud765\uc2dc \uc624\uc774\ub3c4\ub85c 97", "mapx": "284438", "mapy": "528051"}, {"title": "\ud574\uad70\ubcf8\ubd80", "link": "", "category": "\ud55c\uc2dd>\uc0dd\uc120\ud68c", "description": "", "telephone": "031-433-8279", "address": "\uacbd\uae30\ub3c4 \uc2dc\ud765\uc2dc \uc815\uc655\ub3d9 2036-15", "roadAddress": "\uacbd\uae30\ub3c4 \uc2dc\ud765\uc2dc \uc624\uc774\ub3c4\ub85c 233", "mapx": "283909", "mapy": "527387"}, {"title": "\uad6c\ub974\ubbf8", "link": "http://instagram.com/guroomi_caron", "category": "\uc74c\uc2dd\uc810>\uce74\ud398,\ub514\uc800\ud2b8", "description": "", "telephone": "", "address": "\uacbd\uae30\ub3c4 \uc2dc\ud765\uc2dc \uc815\uc655\ub3d9 1857-1", "roadAddress": "\uacbd\uae30\ub3c4 \uc2dc\ud765\uc2dc \uc625\uad6c\uc0c1\uac003\uae38 25 106\ud638", "mapx": "287030", "mapy": "528786"}, {"title": "\ub77c\ub77c\ucf54\uc2a4\ud2b8 \uc2dc\ud765\ubc30\uace7\uc810", "link": "https://www.raracost.com", "category": "\uc74c\uc2dd\uc810>\ud328\ubc00\ub9ac\ub808\uc2a4\ud1a0\ub791", "description": "", "telephone": "031-434-3230", "address": "\uacbd\uae30\ub3c4 \uc2dc\ud765\uc2dc \uc815\uc655\ub3d9 1771-1", "roadAddress": "\uacbd\uae30\ub3c4 \uc2dc\ud765\uc2dc \uc11c\uc6b8\ub300\ud559\ub85c278\ubc88\uae38 61 \ubca0\ub2c8\uc2a4\uc2a4\ud018\uc5b4 3\uce35", "mapx": "287766", "mapy": "530334"}, {"title": "\uc655\uc190\uc870\uac1c\uad6c\uc774\uce7c\uad6d\uc218", "link": "http://www.031-432-5712.kti114.net/", "category": "\ud55c\uc2dd>\uce7c\uad6d\uc218,\ub9cc\ub450", "description": "", "telephone": "031-432-5712", "address": "\uacbd\uae30\ub3c4 \uc2dc\ud765\uc2dc \uc815\uc655\ub3d9 1972-5", "roadAddress": "\uacbd\uae30\ub3c4 \uc2dc\ud765\uc2dc \uc624\uc774\ub3c4\ub85c 127", "mapx": "284163", "mapy": "528149"}, {"title": "\ube14\ub808\uc2a4\ub864 \uc2dc\ud765\ubc30\uace7\uc810", "link": "http://www.instagram.com/cafe_blessroll/", "category": "\uce74\ud398,\ub514\uc800\ud2b8>\uce74\ud398", "description": "", "telephone": "031-499-6704", "address": "\uacbd\uae30\ub3c4 \uc2dc\ud765\uc2dc \uc815\uc655\ub3d9 2475", "roadAddress": "\uacbd\uae30\ub3c4 \uc2dc\ud765\uc2dc \ubc30\uace74\ub85c 18 1\uce35", "mapx": "287417", "mapy": "531426"}, {"title": "\ucee4\ud53c\ubdf0", "link": "http://www.instagram.com/coffeeviewcafe", "category": "\uc74c\uc2dd\uc810>\uce74\ud398,\ub514\uc800\ud2b8", "description": "", "telephone": "", "address": "\uacbd\uae30\ub3c4 \uc2dc\ud765\uc2dc \uc815\uc655\ub3d9 1729-5", "roadAddress": "\uacbd\uae30\ub3c4 \uc2dc\ud765\uc2dc \uc11c\ucd0c\uc0c1\uac003\uae38 7-13", "mapx": "288058", "mapy": "527901"}, {"title": "\uce58\uce75\uce58\uce75 \uc815\uc655\uc5ed\uc810", "link": "https://www.instagram.com/chikakchikak_jeongwang", "category": "\uc74c\uc2dd\uc810>\uce58\ud0a8,\ub2ed\uac15\uc815", "description": "", "telephone": "031-498-7978", "address": "\uacbd\uae30\ub3c4 \uc2dc\ud765\uc2dc \uc815\uc655\ub3d9 2311-12", "roadAddress": "\uacbd\uae30\ub3c4 \uc2dc\ud765\uc2dc \uc624\ub3d9\ub9c8\uc744\ub85c 17", "mapx": "288883", "mapy": "528626"}, {"title": "\ud314\ub3c4\uc2e4\ube44\uc9d1 \ubc30\uace7\uc2e0\ub3c4\uc2dc\uc810", "link": "http://www.instagram.com/zenia4paldo", "category": "\uc220\uc9d1>\ud3ec\uc7a5\ub9c8\ucc28", "description": "", "telephone": "031-499-5867", "address": "\uacbd\uae30\ub3c4 \uc2dc\ud765\uc2dc \uc815\uc655\ub3d9 2515-1", "roadAddress": "\uacbd\uae30\ub3c4 \uc2dc\ud765\uc2dc \uc11c\uc6b8\ub300\ud559\ub85c278\ubc88\uae38 19-8 1\uce35 116\ud638", "mapx": "287580", "mapy": "530518"}, {"title": "\ubb38\uc131 5\ud638", "link": "", "category": "\ud55c\uc2dd>\ud574\ubb3c,\uc0dd\uc120\uc694\ub9ac", "description": "", "telephone": "031-433-2996", "address": "\uacbd\uae30\ub3c4 \uc2dc\ud765\uc2dc \uc815\uc655\ub3d9 2036-17", "roadAddress": "\uacbd\uae30\ub3c4 \uc2dc\ud765\uc2dc \uc624\uc774\ub3c4\ub85c 231", "mapx": "283888", "mapy": "527396"}, {"title": "\uce74\ud398\uc720\uc9c4", "link": "https://instagram.com/j.ujin_", "category": "\uc74c\uc2dd\uc810>\uce74\ud398,\ub514\uc800\ud2b8", "description": "", "telephone": "031-431-8026", "address": "\uacbd\uae30\ub3c4 \uc2dc\ud765\uc2dc \uc815\uc655\ub3d9 1626-1 2\uce35 \uce74\ud398\uc720\uc9c4", "roadAddress": "\uacbd\uae30\ub3c4 \uc2dc\ud765\uc2dc \ud3c9\uc548\uc0c1\uac004\uae38 24-6 \ud30c\ub808\uc2a4\ud638\ud154 2\uce35 \uce74\ud398\uc720\uc9c4", "mapx": "289376", "mapy": "526881"}, {"title": "\ud22c\uc378\ud50c\ub808\uc774\uc2a4 \uc624\uc774\ub3c4\uc528\ud558\uc774\ud638\ud154\uc810", "link": "http://seahihotel.com/", "category": "\uce74\ud398,\ub514\uc800\ud2b8>\uce74\ud398", "description": "", "telephone": "031-319-0048", "address": "\uacbd\uae30\ub3c4 \uc2dc\ud765\uc2dc \uc815\uc655\ub3d9 2031-5", "roadAddress": "\uacbd\uae30\ub3c4 \uc2dc\ud765\uc2dc \uc624\uc774\ub3c4\ub85c135\ubc88\uae38 72", "mapx": "283840", "mapy": "527510"}, {"title": "\ub2ec\ub2ec\ud55c\ud558\ub8e8", "link": "http://www.instagram.com/dal.dal.haru", "category": "\uc74c\uc2dd\uc810>\uce74\ud398,\ub514\uc800\ud2b8", "description": "", "telephone": "", "address": "\uacbd\uae30\ub3c4 \uc2dc\ud765\uc2dc \uc815\uc655\ub3d9 1771-31", "roadAddress": "\uacbd\uae30\ub3c4 \uc2dc\ud765\uc2dc \uc11c\uc6b8\ub300\ud559\ub85c264\ubc88\uae38 35 \uc544\ube0c\ub274\ud504\ub791 \uadf8\ub9b0\ub3d9 107\ud638", "mapx": "287570", "mapy": "530286"}, {"title": "\ub2f4\uace1\uc6d0 \ubcf8\uc810", "link": "", "category": "\ubdd4\ud398>\uace0\uae30\ubdd4\ud398", "description": "", "telephone": "031-499-5775", "address": "\uacbd\uae30\ub3c4 \uc2dc\ud765\uc2dc \uc815\uc655\ub3d9 2476 101,102,103,104\ud638 (\uc815\uc655\ub3d9)", "roadAddress": "\uacbd\uae30\ub3c4 \uc2dc\ud765\uc2dc \ubc30\uace74\ub85c 32-33", "mapx": "287268", "mapy": "531439"}, {"title": "\ub77c\ubb34\uc9c4 \uc2dc\ud765\ubc30\uace7\uc810", "link": "", "category": "\uc74c\uc2dd\uc810>\uc591\uac08\ube44", "description": "", "telephone": "031-498-3738", "address": "\uacbd\uae30\ub3c4 \uc2dc\ud765\uc2dc \uc815\uc655\ub3d9 1775-8", "roadAddress": "\uacbd\uae30\ub3c4 \uc2dc\ud765\uc2dc \uc11c\uc6b8\ub300\ud559\ub85c278\ubc88\uae38 25-18 102\ud638", "mapx": "287634", "mapy": "530516"}, {"title": "\ud22c\uc378\ud50c\ub808\uc774\uc2a4 \uc2dc\ud765\ubc30\uace7\uc810", "link": "http://www.instagram.com/twosomebaegot/", "category": "\uce74\ud398,\ub514\uc800\ud2b8>\uce74\ud398", "description": "", "telephone": "031-498-3545", "address": "\uacbd\uae30\ub3c4 \uc2dc\ud765\uc2dc \uc815\uc655\ub3d9 2513 \uc13c\ud130\ud504\ub77c\uc7901\ucc28 101\ud638", "roadAddress": "\uacbd\uae30\ub3c4 \uc2dc\ud765\uc2dc \ubc30\uace73\ub85c 80 \uc13c\ud130\ud504\ub77c\uc7901\ucc28 101\ud638", "mapx": "287650", "mapy": "530603"}, {"title": "\uce94\ubc84\uc378 canvassom", "link": "http://www.canvassom.com", "category": "\uc74c\uc2dd\uc810>\uce74\ud398,\ub514\uc800\ud2b8", "description": "", "telephone": "031-949-7143", "address": "\uacbd\uae30\ub3c4 \uc2dc\ud765\uc2dc \uc815\uc655\ub3d9 2428-1", "roadAddress": "\uacbd\uae30\ub3c4 \uc2dc\ud765\uc2dc \ubc30\uace7\uc804\uc6d0\ub85c 12-1 1\uce35", "mapx": "287456", "mapy": "531547"}, {"title": "\uc624\uc7a5\ub3d9 \uc22f\ubd88 \ud654\ub85c\uad6c\uc774", "link": "", "category": "\ud55c\uc2dd>\uc721\ub958,\uace0\uae30\uc694\ub9ac", "description": "", "telephone": "031-431-9960", "address": "\uacbd\uae30\ub3c4 \uc2dc\ud765\uc2dc \uc815\uc655\ub3d9 1847", "roadAddress": "\uacbd\uae30\ub3c4 \uc2dc\ud765\uc2dc \uc911\uc2ec\uc0c1\uac00\ub85c 128", "mapx": "287669", "mapy": "528103"}, {"title": "49\ubc88\uac00\ub514\uc800\ud2b8\uce74\ud398", "link": "http://www.facebook.com/49street.hq", "category": "\uce74\ud398,\ub514\uc800\ud2b8>\ubca0\uc774\ucee4\ub9ac", "description": "", "telephone": "", "address": "\uacbd\uae30\ub3c4 \uc2dc\ud765\uc2dc \uc815\uc655\ub3d9 1737-6", "roadAddress": "\uacbd\uae30\ub3c4 \uc2dc\ud765\uc2dc \uc911\uc2ec\uc0c1\uac00\ub85c 187 \uc9c4\uba85\ud504\ub77c\uc790 103\ud638", "mapx": "288216", "mapy": "527718"}, {"title": "\ubd09\uad6c\ud1b5\ub2ed \ubc30\uace7\uc2e0\ub3c4\uc2dc\uc810", "link": "", "category": "\uc74c\uc2dd\uc810>\uce58\ud0a8,\ub2ed\uac15\uc815", "description": "", "telephone": "031-497-0907", "address": "\uacbd\uae30\ub3c4 \uc2dc\ud765\uc2dc \uc815\uc655\ub3d9 2527", "roadAddress": "\uacbd\uae30\ub3c4 \uc2dc\ud765\uc2dc \uc11c\uc6b8\ub300\ud559\ub85c264\ubc88\uae38 35 132~133\ud638", "mapx": "287570", "mapy": "530286"}, {"title": "\ucc3d\uc2e0\ub3d9\ub9e4\uc6b4\uc871\ubc1c \ubc30\uace7\uc810", "link": "", "category": "\ud55c\uc2dd>\uc871\ubc1c,\ubcf4\uc308", "description": "", "telephone": "031-499-3077", "address": "\uacbd\uae30\ub3c4 \uc2dc\ud765\uc2dc \uc815\uc655\ub3d9 2477-3", "roadAddress": "\uacbd\uae30\ub3c4 \uc2dc\ud765\uc2dc \ubc30\uace74\ub85c 32-13", "mapx": "287453", "mapy": "531328"}, {"title": "\uac08\ube44\uba85\uac00\uad81 \uc2dc\ud765\ubc30\uace7\uc810", "link": "", "category": "\ud55c\uc2dd>\uc721\ub958,\uace0\uae30\uc694\ub9ac", "description": "", "telephone": "031-488-9191", "address": "\uacbd\uae30\ub3c4 \uc2dc\ud765\uc2dc \uc815\uc655\ub3d9 2471-1", "roadAddress": "\uacbd\uae30\ub3c4 \uc2dc\ud765\uc2dc \ubc30\uace74\ub85c 99 101-105\ud638", "mapx": "288092", "mapy": "530986"}, {"title": "\ub9c8\ud53c\uc544\ud53c\uc790\uc564\ud38d\ubc30\uace7\uc810", "link": "http://instagram.com/mafiapizza_pubbaegot", "category": "\uc74c\uc2dd\uc810>\ud53c\uc790", "description": "", "telephone": "031-498-5969", "address": "\uacbd\uae30\ub3c4 \uc2dc\ud765\uc2dc \uc815\uc655\ub3d9 2531-1", "roadAddress": "\uacbd\uae30\ub3c4 \uc2dc\ud765\uc2dc \uc11c\uc6b8\ub300\ud559\ub85c264\ubc88\uae38 26-18 122,123\ud638 \ub9c8\ud53c\uc544\ud53c\uc790\uc564\ud38d", "mapx": "287359", "mapy": "530206"}, {"title": "\uc721\uc308\ub0c9\uba74 \ubc30\uace7\uc810", "link": "", "category": "\ud55c\uc2dd>\ub0c9\uba74", "description": "", "telephone": "031-319-1587", "address": "\uacbd\uae30\ub3c4 \uc2dc\ud765\uc2dc \uc815\uc655\ub3d9 2537-2", "roadAddress": "\uacbd\uae30\ub3c4 \uc2dc\ud765\uc2dc \uc11c\uc6b8\ub300\ud559\ub85c278\ubc88\uae38 61", "mapx": "287766", "mapy": "530334"}, {"title": "\uba85\ub95c\uc9c4\uc0ac\uac08\ube44 \uc2dc\ud765\ubc30\uace7\uc810", "link": "", "category": "\ud55c\uc2dd>\uc721\ub958,\uace0\uae30\uc694\ub9ac", "description": "", "telephone": "031-488-9291", "address": "\uacbd\uae30\ub3c4 \uc2dc\ud765\uc2dc \uc815\uc655\ub3d9 2537-2", "roadAddress": "\uacbd\uae30\ub3c4 \uc2dc\ud765\uc2dc \uc11c\uc6b8\ub300\ud559\ub85c278\ubc88\uae38 61 (\uc815\uc655\ub3d9, \uc11c\uc601\ubca0\ub2c8\uc2a4\uc2a4\ud018\uc5b4)", "mapx": "287766", "mapy": "530334"}, {"title": "\uc9c0\uae08\ubcf4\uace0\uc2f6\ub2e4 \uc2dc\ud765\uc815\uc655\uc810", "link": "", "category": "\uc74c\uc2dd\uc810>\uc220\uc9d1>\uc694\ub9ac\uc8fc\uc810", "description": "", "telephone": "", "address": "\uacbd\uae30\ub3c4 \uc2dc\ud765\uc2dc \uc815\uc655\ub3d9 1736-5 1\uce35", "roadAddress": "\uacbd\uae30\ub3c4 \uc2dc\ud765\uc2dc \uc911\uc2ec\uc0c1\uac002\uae38 12-8 1\uce35", "mapx": "288203", "mapy": "527782"}, {"title": "\ud06c\ub798\ud504\ud2b8\uc6d4\ub4dc \ubc30\uace7\uc810", "link": "https://www.facebook.com/CraftworksBaegot/", "category": "\uc220\uc9d1>\ub9e5\uc8fc,\ud638\ud504", "description": "", "telephone": "031-319-7509", "address": "\uacbd\uae30\ub3c4 \uc2dc\ud765\uc2dc \uc815\uc655\ub3d9  2515", "roadAddress": "\uacbd\uae30\ub3c4 \uc2dc\ud765\uc2dc \uc11c\uc6b8\ub300\ud559\ub85c278\ubc88\uae38 19-14", "mapx": "287608", "mapy": "530560"}, {"title": "\uc7a5\uc6d0\ub18d\uc7a5", "link": "http://blog.naver.com/jwfarm", "category": "\ud55c\uc2dd>\ub2ed\uc694\ub9ac", "description": "", "telephone": "031-498-5150", "address": "\uacbd\uae30\ub3c4 \uc2dc\ud765\uc2dc \uc815\uc655\ub3d9 138", "roadAddress": "\uacbd\uae30\ub3c4 \uc2dc\ud765\uc2dc \ubd09\ud654\ub85c143\ubc88\uae38 20", "mapx": "289257", "mapy": "530140"}, {"title": "\ub354\uaf2c\uce58\ub2e4 \ubc30\uace7\uc2e0\ub3c4\uc2dc\uc810", "link": "https://blog.naver.com/msnbumsuk", "category": "\uc220\uc9d1>\uc624\ub385,\uaf2c\uce58", "description": "", "telephone": "031-431-4094", "address": "\uacbd\uae30\ub3c4 \uc2dc\ud765\uc2dc \uc815\uc655\ub3d9 2537-2", "roadAddress": "\uacbd\uae30\ub3c4 \uc2dc\ud765\uc2dc \uc11c\uc6b8\ub300\ud559\ub85c278\ubc88\uae38 61 1\uce35 T-3\ud638", "mapx": "287766", "mapy": "530334"}, {"title": "\ub300\uac00", "link": "", "category": "\ud55c\uc2dd>\uc18c\uace0\uae30\uad6c\uc774", "description": "", "telephone": "031-319-8888", "address": "\uacbd\uae30\ub3c4 \uc2dc\ud765\uc2dc \uc815\uc655\ub3d9 1625-7", "roadAddress": "\uacbd\uae30\ub3c4 \uc2dc\ud765\uc2dc \uc911\uc2ec\uc0c1\uac00\ub85c 327", "mapx": "289302", "mapy": "526854"}, {"title": "\uc625\ucc9c\ubd88\ub09c\uc871\ubc1c \ubc30\uace7\uc810", "link": "", "category": "\ud55c\uc2dd>\uc871\ubc1c,\ubcf4\uc308", "description": "", "telephone": "031-319-7882", "address": "\uacbd\uae30\ub3c4 \uc2dc\ud765\uc2dc \uc815\uc655\ub3d9 2476", "roadAddress": "\uacbd\uae30\ub3c4 \uc2dc\ud765\uc2dc \ubc30\uace74\ub85c 32-33 \ud30c\ud06c\ubdf02 118\ud638 \uc625\ucc9c\ubd88\ub09c\uc871\ubc1c", "mapx": "287271", "mapy": "531437"}, {"title": "\uc124\ube59 \uacbd\uae30\uc2dc\ud765\uc815\uc655\uc810", "link": "http://sulbing.com/", "category": "\uce74\ud398,\ub514\uc800\ud2b8>\ube59\uc218", "description": "", "telephone": "031-497-8088", "address": "\uacbd\uae30\ub3c4 \uc2dc\ud765\uc2dc \uc815\uc655\ub3d9 1742-6 2\uce35", "roadAddress": "\uacbd\uae30\ub3c4 \uc2dc\ud765\uc2dc \uc911\uc2ec\uc0c1\uac003\uae38 24 2\uce35", "mapx": "288179", "mapy": "527667"}, {"title": "\uc544\uc6c3\ub2ed \uc815\uc655\uc810", "link": "http://www.instagram.com/outdark_siheung_jeongwang/", "category": "\uc74c\uc2dd\uc810>\uce58\ud0a8,\ub2ed\uac15\uc815", "description": "", "telephone": "031-499-9095", "address": "\uacbd\uae30\ub3c4 \uc2dc\ud765\uc2dc \uc815\uc655\ub3d9 1741-6 1\uce35", "roadAddress": "\uacbd\uae30\ub3c4 \uc2dc\ud765\uc2dc \uc911\uc2ec\uc0c1\uac001\uae38 3-6 1\uce35", "mapx": "288101", "mapy": "527679"}, {"title": "\ucf69\uc774\ub791\ub450\ubd80\ub791", "link": "", "category": "\ud55c\uc2dd>\ub450\ubd80\uc694\ub9ac", "description": "", "telephone": "031-499-3668", "address": "\uacbd\uae30\ub3c4 \uc2dc\ud765\uc2dc \uc815\uc655\ub3d9 2200-8", "roadAddress": "\uacbd\uae30\ub3c4 \uc2dc\ud765\uc2dc \uc625\ud130\ub85c 67", "mapx": "284195", "mapy": "527469"}, {"title": "\uc0bc\uad6d\uc9c4\ub3fc\uc9c0\uad6d\ubc25", "link": "", "category": "\ud55c\uc2dd>\uad6d\ubc25", "description": "", "telephone": "031-498-8935", "address": "\uacbd\uae30\ub3c4 \uc2dc\ud765\uc2dc \uc815\uc655\ub3d9 2302 1\uce35 \uc0bc\uad6d\uc9c4\ub3fc\uc9c0\uad6d\ubc25", "roadAddress": "\uacbd\uae30\ub3c4 \uc2dc\ud765\uc2dc \ub9c8\uc720\ub85c 415 \uc5ed\uc804\ud504\ub77c\uc790", "mapx": "288619", "mapy": "528499"}, {"title": "\uad7d\ub124\uce58\ud0a8 \uc815\uc6553\ub3d94\ub3d9\uc810", "link": "http://www.goobne.co.kr/", "category": "\uc74c\uc2dd\uc810>\uce58\ud0a8,\ub2ed\uac15\uc815", "description": "", "telephone": "0504-3143-8611", "address": "\uacbd\uae30\ub3c4 \uc2dc\ud765\uc2dc \uc815\uc655\ub3d9 1875-2 \ubbf8\uc8fc\uc544\ud30c\ud2b8\uc0c1\uac00 107\ud638", "roadAddress": "\uacbd\uae30\ub3c4 \uc2dc\ud765\uc2dc \uc815\uc655\uc2e0\uae38\ub85c49\ubc88\uae38 28 \ubbf8\uc8fc\uc544\ud30c\ud2b8 \uc0c1\uac00\ub3d9", "mapx": "287545", "mapy": "529450"}, {"title": "\uad50\ucd0c\uce58\ud0a8 \uc815\uc6553\ud638\uc810", "link": "", "category": "\uc74c\uc2dd\uc810>\uce58\ud0a8,\ub2ed\uac15\uc815", "description": "", "telephone": "031-488-9677", "address": "\uacbd\uae30\ub3c4 \uc2dc\ud765\uc2dc \uc815\uc655\ub3d9 1726-1 \uad11\uac1c\ud1a0\ube4c\ub529 104\ud638", "roadAddress": "\uacbd\uae30\ub3c4 \uc2dc\ud765\uc2dc \uc815\uc655\ub300\ub85c 174", "mapx": "288029", "mapy": "528072"}, {"title": "\ub561\ucd08\uc61b\ub0a0\uce58\ud0a8", "link": "", "category": "\uc74c\uc2dd\uc810>\uce58\ud0a8,\ub2ed\uac15\uc815", "description": "", "telephone": "031-365-4949", "address": "\uacbd\uae30\ub3c4 \uc2dc\ud765\uc2dc \uc815\uc655\ub3d9 2536-1", "roadAddress": "\uacbd\uae30\ub3c4 \uc2dc\ud765\uc2dc \uc11c\uc6b8\ub300\ud559\ub85c264\ubc88\uae38 26-32 104\ud638", "mapx": "287536", "mapy": "530180"}, {"title": "\uc18d\ucd08\uc9d1 \ubcf8\uc810", "link": "", "category": "\ud55c\uc2dd>\ud574\ubb3c,\uc0dd\uc120\uc694\ub9ac", "description": "", "telephone": "031-431-2522", "address": "\uacbd\uae30\ub3c4 \uc2dc\ud765\uc2dc \uc815\uc655\ub3d9 1610-1", "roadAddress": "\uacbd\uae30\ub3c4 \uc2dc\ud765\uc2dc \uc815\uc655\ub300\ub85c233\ubc88\uae38 16", "mapx": "288612", "mapy": "527900"}, {"title": "\ubc25\uc0c1\ucc28\ub9ac\ub294\ub18d\uc0ac\uafbc", "link": "https://blog.naver.com/natureis8570", "category": "\uc74c\uc2dd\uc810>\ud55c\uc2dd", "description": "", "telephone": "031-496-9099", "address": "\uacbd\uae30\ub3c4 \uc2dc\ud765\uc2dc \uc815\uc655\ub3d9 2519-1", "roadAddress": "\uacbd\uae30\ub3c4 \uc2dc\ud765\uc2dc \uc11c\uc6b8\ub300\ud559\ub85c278\ubc88\uae38 43-7 \ubc30\uace7 \uc720\ud638 N-CITY 1\ucc28 1\uce35 127\ud638", "mapx": "287686", "mapy": "530400"}, {"title": "\uac15\uc528\ub124\uce60\ubcf5\ub2ed\uac15\uc815 \ubc30\uace7\uc810", "link": "", "category": "\uc74c\uc2dd\uc810>\uce58\ud0a8,\ub2ed\uac15\uc815", "description": "", "telephone": "031-432-7773", "address": "\uacbd\uae30\ub3c4 \uc2dc\ud765\uc2dc \uc815\uc655\ub3d9 2514 1\uce35 103\ud638", "roadAddress": "\uacbd\uae30\ub3c4 \uc2dc\ud765\uc2dc \ubc30\uace73\ub85c 96 1\uce35 103\ud638", "mapx": "287710", "mapy": "530518"}, {"title": "\ud22c\uc378\ud50c\ub808\uc774\uc2a4 \uc2dc\ud765\uc815\uc655\uc810", "link": "http://www.twosome.co.kr/", "category": "\uce74\ud398,\ub514\uc800\ud2b8>\uce74\ud398", "description": "", "telephone": "031-498-9959", "address": "\uacbd\uae30\ub3c4 \uc2dc\ud765\uc2dc \uc815\uc655\ub3d9 1739-6", "roadAddress": "\uacbd\uae30\ub3c4 \uc2dc\ud765\uc2dc \uc911\uc2ec\uc0c1\uac004\uae38 16-1 \uae38\uc7ac\ube4c\ub529", "mapx": "288360", "mapy": "527633"}, {"title": "\uc5f0\uc548<b>\uc2dd\ub2f9</b> \uc2dc\ud654\uc815\uc655\uc810", "link": "http://yeonansikdang.co.kr/", "category": "\ud55c\uc2dd>\ud574\ubb3c,\uc0dd\uc120\uc694\ub9ac", "description": "", "telephone": "031-434-9688", "address": "\uacbd\uae30\ub3c4 \uc2dc\ud765\uc2dc \uc815\uc655\ub3d9 1853-1", "roadAddress": "\uacbd\uae30\ub3c4 \uc2dc\ud765\uc2dc \uc625\uad6c\uc0c1\uac001\uae38 23 \uccad\ud55c\ube4c\ub529 1\uce35", "mapx": "286940", "mapy": "528689"}, {"title": "60\uacc4 \uce58\ud0a8 \ubc30\uace7\uc2e0\ub3c4\uc2dc\uc810", "link": "http://www.60chicken.co.kr", "category": "\uc74c\uc2dd\uc810>\uce58\ud0a8,\ub2ed\uac15\uc815", "description": "", "telephone": "031-497-9100", "address": "\uacbd\uae30\ub3c4 \uc2dc\ud765\uc2dc \uc815\uc655\ub3d9 1771-31", "roadAddress": "\uacbd\uae30\ub3c4 \uc2dc\ud765\uc2dc \uc11c\uc6b8\ub300\ud559\ub85c278\ubc88\uae38 26 104\ud638 (\uc815\uc655\ub3d9, \uc2dc\ud765\ubc30\uace7 \uc544\ube0c\ub274\ud504\ub791 \uc13c\ud2b8\ub7f4\uc624\ub80c\uc9c0)", "mapx": "287516", "mapy": "530418"}, {"title": "\uc6b0\uac15 \ubbfc\ubb3c\uc7a5\uc5b4", "link": "", "category": "\ud55c\uc2dd>\uc7a5\uc5b4,\uba39\uc7a5\uc5b4\uc694\ub9ac", "description": "", "telephone": "031-433-0592", "address": "\uacbd\uae30\ub3c4 \uc2dc\ud765\uc2dc \uc815\uc655\ub3d9 1856-4", "roadAddress": "\uacbd\uae30\ub3c4 \uc2dc\ud765\uc2dc \uc625\uad6c\ucc9c\uc11c\ub85c 313 1\uce35 \uc6b0\uac15\ubbfc\ubb3c\uc7a5\uc5b4", "mapx": "287061", "mapy": "528475"}, {"title": "\ud55c\uc2e0\ud3ec\ucc28 \ubc30\uace7\uc2e0\ub3c4\uc2dc\uc810", "link": "http://hspocha.itrocks.kr/", "category": "\uc220\uc9d1>\ud3ec\uc7a5\ub9c8\ucc28", "description": "", "telephone": "031-497-4999", "address": "\uacbd\uae30\ub3c4 \uc2dc\ud765\uc2dc \uc815\uc655\ub3d9 2514", "roadAddress": "\uacbd\uae30\ub3c4 \uc2dc\ud765\uc2dc \ubc30\uace73\ub85c 96 M-\ud50c\ub7ec\uc2a4", "mapx": "287701", "mapy": "530538"}, {"title": "\ub6b1\ubcf4\uc9d1 \ubc30\uace7\uc810", "link": "http://www.pighouse.co.kr", "category": "\ud55c\uc2dd>\ub3fc\uc9c0\uace0\uae30\uad6c\uc774", "description": "", "telephone": "031-498-6333", "address": "\uacbd\uae30\ub3c4 \uc2dc\ud765\uc2dc \uc815\uc655\ub3d9 2513-1", "roadAddress": "\uacbd\uae30\ub3c4 \uc2dc\ud765\uc2dc \ubc30\uace73\ub85c 86", "mapx": "287670", "mapy": "530553"}, {"title": "\ub728\ub048\uc774\uac10\uc790\ud0d5 \uc2dc\ud654\uc774\ub9c8\ud2b8\uc810", "link": "", "category": "\ud55c\uc2dd>\uac10\uc790\ud0d5", "description": "", "telephone": "031-433-7578", "address": "\uacbd\uae30\ub3c4 \uc2dc\ud765\uc2dc \uc815\uc655\ub3d9 1745-5", "roadAddress": "\uacbd\uae30\ub3c4 \uc2dc\ud765\uc2dc \uc911\uc2ec\uc0c1\uac001\uae38 18 \uc8fc\ucc28\ud0c0\uc6cc", "mapx": "288118", "mapy": "527533"}, {"title": "\uc6c5\uc774\ub124 \uc624\ub3cc\ubf08", "link": "http://cafe.daum.net/Woong2ne-house/", "category": "\ud55c\uc2dd>\ub2ed\ubc1c", "description": "", "telephone": "031-431-9278", "address": "\uacbd\uae30\ub3c4 \uc2dc\ud765\uc2dc \uc815\uc655\ub3d9 1592", "roadAddress": "\uacbd\uae30\ub3c4 \uc2dc\ud765\uc2dc \uc815\uc655\ucc9c\ub85c369\ubc88\uae38 59-1 \ub3d9\uc2e0\ud765\uc0b0\ube4c\ub529", "mapx": "288915", "mapy": "527719"}, {"title": "\uc7a5\ud601\ubbfc\uc758\ubd80\ub300\ucc0c\uac1c \ubc30\uace7\uc810", "link": "", "category": "\uc74c\uc2dd\uc810>\ud55c\uc2dd", "description": "", "telephone": "031-319-0137", "address": "\uacbd\uae30\ub3c4 \uc2dc\ud765\uc2dc \uc815\uc655\ub3d9 2477-3", "roadAddress": "\uacbd\uae30\ub3c4 \uc2dc\ud765\uc2dc \ubc30\uace74\ub85c 32-13 \uc720\ud14c\ub77c\uc2a4\ube4c\ub529204\ud638", "mapx": "287446", "mapy": "531317"}, {"title": "\uc778\ud558\ucc39\uc300\uc21c\ub300", "link": "", "category": "\ud55c\uc2dd>\uc21c\ub300,\uc21c\ub313\uad6d", "description": "", "telephone": "031-497-7708", "address": "\uacbd\uae30\ub3c4 \uc2dc\ud765\uc2dc \uc815\uc655\ub3d9 1771-31 114\ud638,115\ud638", "roadAddress": "\uacbd\uae30\ub3c4 \uc2dc\ud765\uc2dc \uc11c\uc6b8\ub300\ud559\ub85c278\ubc88\uae38 26 114\ud638,115\ud638", "mapx": "287516", "mapy": "530418"}, {"title": "10ozcoffee", "link": "http://instagram.com/10ozcoffee", "category": "\uce74\ud398,\ub514\uc800\ud2b8>\uce74\ud398", "description": "", "telephone": "", "address": "\uacbd\uae30\ub3c4 \uc2dc\ud765\uc2dc \uc815\uc655\ub3d9 1624-8", "roadAddress": "\uacbd\uae30\ub3c4 \uc2dc\ud765\uc2dc \uc911\uc2ec\uc0c1\uac00\ub85c 317", "mapx": "289226", "mapy": "526921"}, {"title": "\uad6c\uc774\uac00", "link": "", "category": "\ud55c\uc2dd>\uc0dd\uc120\uad6c\uc774", "description": "", "telephone": "031-497-3757", "address": "\uacbd\uae30\ub3c4 \uc2dc\ud765\uc2dc \uc815\uc655\ub3d9 2309-8", "roadAddress": "\uacbd\uae30\ub3c4 \uc2dc\ud765\uc2dc \uc624\ub3d9\ub9c8\uc744\ub85c 13", "mapx": "288861", "mapy": "528627"}, {"title": "88\ucf04\ud130\ud0a4 \uc815\uc6551\ud638\uc810", "link": "", "category": "\uc74c\uc2dd\uc810>\uce58\ud0a8,\ub2ed\uac15\uc815", "description": "", "telephone": "031-498-8870", "address": "\uacbd\uae30\ub3c4 \uc2dc\ud765\uc2dc \uc815\uc655\ub3d9 1884-3", "roadAddress": "\uacbd\uae30\ub3c4 \uc2dc\ud765\uc2dc \ud568\uc1a1\ub85c14\ubc88\uae38 13-15 1\uce35", "mapx": "287652", "mapy": "529755"}, {"title": "\ub9c8\uc655\uc871\ubc1c \ubc30\uace7\uc2e0\ub3c4\uc2dc\uc810", "link": "http://mawangpork.com/", "category": "\uc721\ub958,\uace0\uae30\uc694\ub9ac>\uc871\ubc1c,\ubcf4\uc308", "description": "", "telephone": "031-432-2005", "address": "\uacbd\uae30\ub3c4 \uc2dc\ud765\uc2dc \uc815\uc655\ub3d9 2537-2", "roadAddress": "\uacbd\uae30\ub3c4 \uc2dc\ud765\uc2dc \uc11c\uc6b8\ub300\ud559\ub85c278\ubc88\uae38 61 \ubca0\ub2c8\uc2a4\uc2a4\ud018\uc5b4 1\uce35 C-8\ud638 (\uc8fc\ubbfc\uc13c\ud130 \uac74\ubb3c)", "mapx": "287766", "mapy": "530334"}, {"title": "\ud638\uce58\ubbfc\ubd09\uc528", "link": "", "category": "\uc74c\uc2dd\uc810>\uce58\ud0a8,\ub2ed\uac15\uc815", "description": "", "telephone": "031-497-0704", "address": "\uacbd\uae30\ub3c4 \uc2dc\ud765\uc2dc \uc815\uc655\ub3d9 2518-1 \ub2e4\uc778\ub85c\uc584\ud330\ub9ac\uc2a4\ubc30\uace72\ucc28 101\ud638", "roadAddress": "\uacbd\uae30\ub3c4 \uc2dc\ud765\uc2dc \uc11c\uc6b8\ub300\ud559\ub85c278\ubc88\uae38 25-32 \ub2e4\uc778\ub85c\uc584\ud330\ub9ac\uc2a4\ubc30\uace72\ucc28 101\ud638", "mapx": "287651", "mapy": "530450"}, {"title": "\uc218\ub0b4\ub2ed\uaf2c\uce58", "link": "", "category": "\uc220\uc9d1>\uc624\ub385,\uaf2c\uce58", "description": "", "telephone": "031-499-5792", "address": "\uacbd\uae30\ub3c4 \uc2dc\ud765\uc2dc \uc815\uc655\ub3d9 2475-1", "roadAddress": "\uacbd\uae30\ub3c4 \uc2dc\ud765\uc2dc \ubc30\uace74\ub85c 22 \ubc30\uace7\ud0c0\uc6b4 129\ud638", "mapx": "287458", "mapy": "531389"}, {"title": "\uce74\ud398\ubaa8\ub450", "link": "", "category": "\uce74\ud398,\ub514\uc800\ud2b8>\uce74\ud398", "description": "", "telephone": "031-498-0308", "address": "\uacbd\uae30\ub3c4 \uc2dc\ud765\uc2dc \uc815\uc655\ub3d9 2537-2", "roadAddress": "\uacbd\uae30\ub3c4 \uc2dc\ud765\uc2dc \uc11c\uc6b8\ub300\ud559\ub85c278\ubc88\uae38 61 \ubca0\ub2c8\uc2a4 \uc2a4\ud018\uc5b4 1\uce35 s7\ud638", "mapx": "287766", "mapy": "530334"}, {"title": "\uc774\ub514\uc57c\ucee4\ud53c \uc2dc\ud765\ubc30\uace7CGV\uc810", "link": "http://www.ediya.com/", "category": "\uce74\ud398,\ub514\uc800\ud2b8>\uce74\ud398", "description": "", "telephone": "031-499-5331", "address": "\uacbd\uae30\ub3c4 \uc2dc\ud765\uc2dc \uc815\uc655\ub3d9 1771-1", "roadAddress": "\uacbd\uae30\ub3c4 \uc2dc\ud765\uc2dc \uc11c\uc6b8\ub300\ud559\ub85c278\ubc88\uae38 61 \ubca0\ub2c8\uc2a4 \uc2a4\ud018\uc5b4 710\ud638", "mapx": "287766", "mapy": "530334"}, {"title": "\uc220\ucd0c", "link": "", "category": "\uc74c\uc2dd\uc810>\ud55c\uc2dd", "description": "", "telephone": "", "address": "\uacbd\uae30\ub3c4 \uc2dc\ud765\uc2dc \uc815\uc655\ub3d9 2321-9 1\uce35 \uc220\ucd0c", "roadAddress": "\uacbd\uae30\ub3c4 \uc2dc\ud765\uc2dc \uc624\ub3d9\ub9c8\uc744\ub85c6\ubc88\uae38 15", "mapx": "288788", "mapy": "528555"}, {"title": "\uc2a4\ud0c0\ubc85\uc2a4 \ubc30\uace7\uc544\ube0c\ub274\ud504\ub791\uc810", "link": "http://www.starbucks.co.kr/", "category": "\uce74\ud398,\ub514\uc800\ud2b8>\uce74\ud398", "description": "", "telephone": "1522-3232", "address": "\uacbd\uae30\ub3c4 \uc2dc\ud765\uc2dc \uc815\uc655\ub3d9 1771-31 \uc2dc\ud765\ubc30\uace7 \uc544\ube0c\ub274\ud504\ub791 \uc13c\ud2b8\ub7f4 \uc610\ub85c\uc6b0 117,118,119,120,121\ud638", "roadAddress": "\uacbd\uae30\ub3c4 \uc2dc\ud765\uc2dc \uc11c\uc6b8\ub300\ud559\ub85c264\ubc88\uae38 19", "mapx": "287653", "mapy": "530340"}, {"title": "\ubc30\ubd80\uc7a5\ucc0c\uac1c <b>\uc815\uc655\ub3d9</b>\uc810", "link": "http://boglbogl.co.kr/", "category": "\ud55c\uc2dd>\ucc0c\uac1c,\uc804\uace8", "description": "", "telephone": "031-431-5977", "address": "\uacbd\uae30\ub3c4 \uc2dc\ud765\uc2dc \uc815\uc655\ub3d9 1739-5 \ud558\uc601\ube4c\ub529", "roadAddress": "\uacbd\uae30\ub3c4 \uc2dc\ud765\uc2dc \uc911\uc2ec\uc0c1\uac004\uae38 16 \ud558\uc601\ube4c\ub529", "mapx": "288361", "mapy": "527659"}, {"title": "\uc774\ud0c4\uc9d1 \uc2dc\ud765\ubc30\uace7\uc810", "link": "http://leetanjip.com/", "category": "\ud55c\uc2dd>\uacf1\ucc3d,\ub9c9\ucc3d,\uc591", "description": "", "telephone": "031-497-8898", "address": "\uacbd\uae30\ub3c4 \uc2dc\ud765\uc2dc \uc815\uc655\ub3d9 2522 1\uce35 123~125\ud638", "roadAddress": "\uacbd\uae30\ub3c4 \uc2dc\ud765\uc2dc \uc11c\uc6b8\ub300\ud559\ub85c278\ubc88\uae38 8 1\uce35 123~125\ud638", "mapx": "287403", "mapy": "530505"}, {"title": "\uc0b4\ucc0c\ub294\ucf00\uc774\ud06c 2\ud638\uc810", "link": "", "category": "\uc74c\uc2dd\uc810>\uce74\ud398,\ub514\uc800\ud2b8", "description": "", "telephone": "031-499-7271", "address": "\uacbd\uae30\ub3c4 \uc2dc\ud765\uc2dc \uc815\uc655\ub3d9 1880-8", "roadAddress": "\uacbd\uae30\ub3c4 \uc2dc\ud765\uc2dc \ud568\uc1a1\ub85c13\ubc88\uae38 6-15 2\uce35", "mapx": "287817", "mapy": "529922"}, {"title": "\uc7a5\ucda9\ub2f9 \uc2dc\ud654\uc815\uc655\uc810", "link": "", "category": "\uc721\ub958,\uace0\uae30\uc694\ub9ac>\uc871\ubc1c,\ubcf4\uc308", "description": "", "telephone": "031-431-0007", "address": "\uacbd\uae30\ub3c4 \uc2dc\ud765\uc2dc \uc815\uc655\ub3d9 1782-5", "roadAddress": "\uacbd\uae30\ub3c4 \uc2dc\ud765\uc2dc \uc911\uc2ec\uc0c1\uac00\ub85c 320", "mapx": "289220", "mapy": "526870"}, {"title": "\uc11c\ucd08\ub3d9\uc5f0\uac00 \ubc30\uace7\uc810", "link": "http://www.instagram.com/jieun8890", "category": "\ud55c\uc2dd>\uc721\ub958,\uace0\uae30\uc694\ub9ac", "description": "", "telephone": "031-432-7228", "address": "\uacbd\uae30\ub3c4 \uc2dc\ud765\uc2dc \uc815\uc655\ub3d9 2518 1\uce35", "roadAddress": "\uacbd\uae30\ub3c4 \uc2dc\ud765\uc2dc \uc11c\uc6b8\ub300\ud559\ub85c278\ubc88\uae38 25-24 1\uce35", "mapx": "287677", "mapy": "530483"}, {"title": "\ud30c\ub9ac\ubc14\uac8c\ub728 \uc2dc\ud654\uc815\uc655\uc810", "link": "http://www.paris.co.kr/", "category": "\uce74\ud398,\ub514\uc800\ud2b8>\ubca0\uc774\ucee4\ub9ac", "description": "", "telephone": "031-497-8204", "address": "\uacbd\uae30\ub3c4 \uc2dc\ud765\uc2dc \uc815\uc655\ub3d9 1737-21", "roadAddress": "\uacbd\uae30\ub3c4 \uc2dc\ud765\uc2dc \uc911\uc2ec\uc0c1\uac00\ub85c 199 \uc9c0\uc131\ud504\ub77c\uc790(\uc911\uc2ec\uc0c1\uac00\ub85c 48)", "mapx": "288314", "mapy": "527639"}, {"title": "\ucb48\uafb8\ubbf8\uc0bc\uacb9\uc0b4", "link": "", "category": "\ud55c\uc2dd>\uc8fc\uafb8\ubbf8\uc694\ub9ac", "description": "", "telephone": "0507-0493-0089", "address": "\uacbd\uae30\ub3c4 \uc2dc\ud765\uc2dc \uc815\uc655\ub3d9 1731-17 \uc2e0\uc544\ud504\ub77c\uc790", "roadAddress": "\uacbd\uae30\ub3c4 \uc2dc\ud765\uc2dc \uc11c\ucd0c\uc0c1\uac002\uae38 25", "mapx": "287917", "mapy": "527876"}, {"title": "\uc73c\ub738\ub0a8\ub3c4<b>\ub9db\uc9d1</b>", "link": "http://namdotaste.modoo.at/", "category": "\uc74c\uc2dd\uc810>\ud55c\uc2dd", "description": "", "telephone": "031-431-1594", "address": "\uacbd\uae30\ub3c4 \uc2dc\ud765\uc2dc \uc815\uc655\ub3d9 2310-1", "roadAddress": "\uacbd\uae30\ub3c4 \uc2dc\ud765\uc2dc \ub9c8\uc720\ub85c446\ubc88\uae38 18 \ucc2c\ud604\ube4c\ub529", "mapx": "288917", "mapy": "528705"}, {"title": "\uc774\ubc14\ub3d4\uac10\uc790\ud0d5 \uc2dc\ud765\uc815\uc655\uc810", "link": "http://www.ebadom.com/", "category": "\ud55c\uc2dd>\uac10\uc790\ud0d5", "description": "", "telephone": "031-488-8990", "address": "\uacbd\uae30\ub3c4 \uc2dc\ud765\uc2dc \uc815\uc655\ub3d9 1622-2", "roadAddress": "\uacbd\uae30\ub3c4 \uc2dc\ud765\uc2dc \uc815\uc655\ub300\ub85c 348", "mapx": "289351", "mapy": "527033"}, {"title": "\ud53c\uc790\ud5d0", "link": "", "category": "\uc74c\uc2dd\uc810>\ud53c\uc790", "description": "", "telephone": "0504-3142-4882", "address": "\uacbd\uae30\ub3c4 \uc2dc\ud765\uc2dc \uc815\uc655\ub3d9 1419-18 1\uce35 103\ud638", "roadAddress": "\uacbd\uae30\ub3c4 \uc2dc\ud765\uc2dc \ud070\uc194\ub85c22\ubc88\uae38 2", "mapx": "289645", "mapy": "527120"}, {"title": "\uc77c\uacf5\uce60\uce74\ud398\ud38d", "link": "", "category": "\uc74c\uc2dd\uc810>\uce74\ud398,\ub514\uc800\ud2b8", "description": "", "telephone": "", "address": "\uacbd\uae30\ub3c4 \uc2dc\ud765\uc2dc \uc815\uc655\ub3d9 2549", "roadAddress": "\uacbd\uae30\ub3c4 \uc2dc\ud765\uc2dc \uc11c\uc6b8\ub300\ud559\ub85c264\ubc88\uae38 50 A\ub3d9 107\ud638", "mapx": "287607", "mapy": "530160"}, {"title": "\uc774\ub514\uc57c\ucee4\ud53c \uc2dc\ud765\ud55c\ub77c\ube44\ubc1c\ub514\uc810", "link": "http://www.ediya.com/", "category": "\uce74\ud398,\ub514\uc800\ud2b8>\uce74\ud398", "description": "", "telephone": "031-432-7333", "address": "\uacbd\uae30\ub3c4 \uc2dc\ud765\uc2dc \uc815\uc655\ub3d9 2566 \ud55c\ub77c\ube44\ubc1c\ub514\ucea0\ud37c\uc2a4", "roadAddress": "\uacbd\uae30\ub3c4 \uc2dc\ud765\uc2dc \ubc30\uace71\ub85c 27-15 \ud55c\ub77c\ube44\ubc1c\ub514\ucea0\ud37c\uc2a4", "mapx": "286176", "mapy": "529723"}, {"title": "\ub81b\uce20\uace0\ud638\ud504", "link": "http://LetsGo.cityfood.co.kr", "category": "\uc220\uc9d1>\ub9e5\uc8fc,\ud638\ud504", "description": "", "telephone": "031-432-4501", "address": "\uacbd\uae30\ub3c4 \uc2dc\ud765\uc2dc \uc815\uc655\ub3d9 1771-1", "roadAddress": "\uacbd\uae30\ub3c4 \uc2dc\ud765\uc2dc \uc11c\uc6b8\ub300\ud559\ub85c278\ubc88\uae38 25-32 207\ud638", "mapx": "287648", "mapy": "530433"}, {"title": "\uc5ec\uc790\ub9d0\uc744\uc798\ub4e3\uc790 \uc2dc\ud765\uc2dc\ud654\uc810", "link": "", "category": "\uc220\uc9d1>\uc694\ub9ac\uc8fc\uc810", "description": "", "telephone": "031-504-5858", "address": "\uacbd\uae30\ub3c4 \uc2dc\ud765\uc2dc \uc815\uc655\ub3d9 1742-7 \uc1a1\ud504\ub77c\uc790 304\ud638", "roadAddress": "\uacbd\uae30\ub3c4 \uc2dc\ud765\uc2dc \uc911\uc2ec\uc0c1\uac003\uae38 26 \uc1a1\ud504\ub77c\uc790 304\ud638", "mapx": "288167", "mapy": "527658"}, {"title": "\ud55c\uc1a5\ub3c4\uc2dc\ub77d \uc2dc\ud654\uc138\uc885\uc810", "link": "http://www.hsd.co.kr", "category": "\uc74c\uc2dd\uc810>\ub3c4\uc2dc\ub77d,\ucef5\ubc25", "description": "", "telephone": "031-434-9494", "address": "\uacbd\uae30\ub3c4 \uc2dc\ud765\uc2dc \uc815\uc655\ub3d9 1882-8 106\ud638", "roadAddress": "\uacbd\uae30\ub3c4 \uc2dc\ud765\uc2dc \uc815\uc655\uc2e0\uae38\ub85c49\ubc88\uae38 61 \uc6a9\ub9c8\ud504\ub77c\uc790", "mapx": "287732", "mapy": "529734"}, {"title": "\ud649\uc288\ud06c\ub9bc", "link": "", "category": "\uc74c\uc2dd\uc810>\uce74\ud398,\ub514\uc800\ud2b8>\ubca0\uc774\ucee4\ub9ac", "description": "", "telephone": "031-498-8060", "address": "\uacbd\uae30\ub3c4 \uc2dc\ud765\uc2dc \uc815\uc655\ub3d9 1775-8 \ub2e4\uc778\ub85c\uc584\ud330\ub9ac\uc2a4\ubc30\uace73\ucc28 1\uce35 109\ud638", "roadAddress": "\uacbd\uae30\ub3c4 \uc2dc\ud765\uc2dc \uc11c\uc6b8\ub300\ud559\ub85c278\ubc88\uae38 25-18 \ub2e4\uc778\ub85c\uc584\ud330\ub9ac\uc2a4\ubc30\uace73\ucc28 1\uce35 109\ud638", "mapx": "287633", "mapy": "530497"}, {"title": "\ubb34\uad50\ub3d9\ub099\uc9c0\uc2dc\ud654\uc810", "link": "", "category": "\ud55c\uc2dd>\ub099\uc9c0\uc694\ub9ac", "description": "", "telephone": "031-433-7705", "address": "\uacbd\uae30\ub3c4 \uc2dc\ud765\uc2dc \uc815\uc655\ub3d9 1736-5", "roadAddress": "\uacbd\uae30\ub3c4 \uc2dc\ud765\uc2dc \uc911\uc2ec\uc0c1\uac002\uae38 12-8 \uc815\uc655\uc8fc\ucc28\ud0c0\uc6b4", "mapx": "288213", "mapy": "527768"}, {"title": "\ub458\ub458\uce58\ud0a8 \uc815\uc655\uc810", "link": "http://www.22chicken.co.kr/", "category": "\uc74c\uc2dd\uc810>\uce58\ud0a8,\ub2ed\uac15\uc815", "description": "", "telephone": "0504-0953-0416", "address": "\uacbd\uae30\ub3c4 \uc2dc\ud765\uc2dc \uc815\uc655\ub3d9 1742-21", "roadAddress": "\uacbd\uae30\ub3c4 \uc2dc\ud765\uc2dc \uc911\uc2ec\uc0c1\uac003\uae38 31-1", "mapx": "288159", "mapy": "527637"}, {"title": "\ud380\ube44\uc5b4\ud0b9 \uc2dc\ud765 \uc2dc\ud654\ubcd1\uc6d0\uc810", "link": "http://www.funbeerking.com", "category": "\uc220\uc9d1>\ub9e5\uc8fc,\ud638\ud504", "description": "", "telephone": "031-497-5111", "address": "\uacbd\uae30\ub3c4 \uc2dc\ud765\uc2dc \uc815\uc655\ub3d9 1861-6", "roadAddress": "\uacbd\uae30\ub3c4 \uc2dc\ud765\uc2dc \uc625\uad6c\uc0c1\uac002\uae38 3", "mapx": "287172", "mapy": "528724"}, {"title": "\uac10\ub3d9\uba39\ud0dc", "link": "", "category": "\uc220\uc9d1>\ub9e5\uc8fc,\ud638\ud504", "description": "", "telephone": "032-499-3621", "address": "\uacbd\uae30\ub3c4 \uc2dc\ud765\uc2dc \uc815\uc655\ub3d9 2515 \ubc30\uace7\ud504\ub77c\uc790 1\uce35 102\ud638", "roadAddress": "\uacbd\uae30\ub3c4 \uc2dc\ud765\uc2dc \uc11c\uc6b8\ub300\ud559\ub85c278\ubc88\uae38 19-14 \ubc30\uace7\ud504\ub77c\uc790 1\uce35 102\ud638", "mapx": "287600", "mapy": "530542"}, {"title": "\uc624\ubc15\uc9d1", "link": "", "category": "\ud55c\uc2dd>\ub3fc\uc9c0\uace0\uae30\uad6c\uc774", "description": "", "telephone": "031-319-0665", "address": "\uacbd\uae30\ub3c4 \uc2dc\ud765\uc2dc \uc815\uc655\ub3d9 1885-6", "roadAddress": "\uacbd\uae30\ub3c4 \uc2dc\ud765\uc2dc \ud568\uc1a1\ub85c14\ubc88\uae38 13-10", "mapx": "287626", "mapy": "529725"}, {"title": "\uccad\uae30\uc640\uac10\uc790\ud0d5 \ubc30\uace7\uc2e0\ub3c4\uc2dc\uc810", "link": "", "category": "\ud55c\uc2dd>\uac10\uc790\ud0d5", "description": "", "telephone": "031-433-7752", "address": "\uacbd\uae30\ub3c4 \uc2dc\ud765\uc2dc \uc815\uc655\ub3d9 1771-31", "roadAddress": "\uacbd\uae30\ub3c4 \uc2dc\ud765\uc2dc \uc11c\uc6b8\ub300\ud559\ub85c278\ubc88\uae38 8", "mapx": "287403", "mapy": "530505"}, {"title": "\ud6cc\ub784\ub77c\uc22f\ubd88\uce58\ud0a8 \ubc30\uace71\uc810", "link": "", "category": "\uc74c\uc2dd\uc810>\uce58\ud0a8,\ub2ed\uac15\uc815", "description": "", "telephone": "031-432-2020", "address": "\uacbd\uae30\ub3c4 \uc2dc\ud765\uc2dc \uc815\uc655\ub3d9 1771-24", "roadAddress": "\uacbd\uae30\ub3c4 \uc2dc\ud765\uc2dc \uc11c\ud574\uc548\ub85c 529 \ub450\uc190\uc9c0\uc824\ud0c0\uc6cc B\ub3d9 105\ud638", "mapx": "287889", "mapy": "530297"}, {"title": "\uba55\uc2dc\uce74\ub098\uce58\ud0a8 \uc815\uc655\uc810", "link": "http://0314999282.bdp.kr/", "category": "\uc74c\uc2dd\uc810>\uce58\ud0a8,\ub2ed\uac15\uc815", "description": "", "telephone": "", "address": "\uacbd\uae30\ub3c4 \uc2dc\ud765\uc2dc \uc815\uc655\ub3d9 2164-2", "roadAddress": "\uacbd\uae30\ub3c4 \uc2dc\ud765\uc2dc \ud611\ub825\ub85c 281 \uba54\uac00\ud3f4\ub9ac\uc2a4(\uacf5\ub2e82\ub85c 6)", "mapx": "286425", "mapy": "528539"}, {"title": "\ud64d\ud76c\ud1b5\ub2ed \uc815\uc655\uc5ed\uc810", "link": "", "category": "\uc74c\uc2dd\uc810>\uce58\ud0a8,\ub2ed\uac15\uc815", "description": "", "telephone": "031-497-9998", "address": "\uacbd\uae30\ub3c4 \uc2dc\ud765\uc2dc \uc815\uc655\ubcf8\ub3d9 2298-7", "roadAddress": "\uacbd\uae30\ub3c4 \uc2dc\ud765\uc2dc \ub9c8\uc720\ub85c423\ubc88\uae38 12-1", "mapx": "288557", "mapy": "528631"}]